{
  "sources": [
    { "type": "arxiv", "name": "arXiv", "enabled": false }
  ],
  "conference_sources": {
    "enabled": true,
    "years": [2026, 2025],
    "venues": [
      {
        "id": "icml",
        "name": "ICML",
        "group": "machine learning",
        "dblp_toc_patterns": ["db/conf/icml/icml{year}.bht"]
      },
      {
        "id": "iclr",
        "name": "ICLR",
        "group": "machine learning",
        "dblp_toc_patterns": ["db/conf/iclr/iclr{year}.bht"]
      },
      {
        "id": "neurips",
        "name": "NeurIPS",
        "group": "machine learning",
        "dblp_toc_patterns": [
          "db/conf/nips/nips{year}.bht",
          "db/conf/neurips/neurips{year}.bht"
        ]
      },
      {
        "id": "acl",
        "name": "ACL",
        "group": "natural language processing",
        "dblp_toc_patterns": [
          "db/conf/acl/acl{year}-1.bht",
          "db/conf/acl/acl{year}-2.bht"
        ]
      },
      {
        "id": "cvpr",
        "name": "CVPR",
        "group": "computer vision",
        "dblp_toc_patterns": ["db/conf/cvpr/cvpr{year}.bht"]
      }
    ]
  },
  "topics": [
    {
      "id": "mllm_hallucination_factuality",
      "name": "多模态大模型幻觉与事实性",
      "description": "面向真实顶会检索的宽召回主题，覆盖 MLLM/LVLM/VLM/audio-visual/video multimodal models 中的 hallucination、object hallucination、visual hallucination、cross-modal hallucination、factuality、faithfulness、grounding failure 和模型输出是否被视觉证据支持的问题。",
      "keywords": [
        "hallucination",
        "hallucinations",
        "multimodal hallucination",
        "multimodal large language model",
        "MLLM hallucination",
        "LVLM hallucination",
        "VLM hallucination",
        "visual hallucination",
        "object hallucination",
        "cross-modal hallucination",
        "cross-lingual cross-modal hallucination",
        "vision-language hallucination",
        "large vision-language model",
        "large vision language model",
        "audio-visual large language model",
        "video large language model",
        "multimodal factuality",
        "multimodal faithfulness",
        "visual grounding",
        "grounding failure",
        "groundedness",
        "caption faithfulness",
        "image captioning hallucination"
      ],
      "arxiv_categories": ["cs.CV", "cs.CL", "cs.AI", "cs.LG"]
    },
    {
      "id": "mllm_hallucination_mitigation_alignment",
      "name": "幻觉缓解、对齐与解码",
      "description": "覆盖真实论文中常见的 hallucination mitigation 路线，包括 decoding、attention/activation steering、visual signal enhancement、DPO/RLHF/RLAIF/preference optimization、reward model、self-correction、training-free mitigation 和 post-training alignment。",
      "keywords": [
        "hallucination mitigation",
        "hallucination suppression",
        "mitigate hallucinations",
        "reducing hallucinations",
        "alleviating hallucinations",
        "visual evidence prompting",
        "image-grounded guidance",
        "contrastive decoding",
        "grounded decoding",
        "selective decoding",
        "activation steering",
        "attention intervention",
        "visual signal enhancement",
        "visual-aware token",
        "HalluSpace",
        "on-policy data",
        "self-correction hallucination",
        "hallucination-aware instruction tuning",
        "multimodal preference optimization",
        "DPO hallucination",
        "direct preference optimization hallucination",
        "RLHF hallucination",
        "RLAIF hallucination",
        "reward model hallucination",
        "faithfulness reward",
        "grounding-aware training",
        "post-training hallucination"
      ],
      "arxiv_categories": ["cs.CV", "cs.CL", "cs.AI", "cs.LG"]
    },
    {
      "id": "mllm_hallucination_detection_benchmark_attribution",
      "name": "幻觉检测、基准与归因分析",
      "description": "覆盖 hallucination detection、benchmark、evaluation dataset、token-level localization、visual evidence attribution、attention head analysis、language prior、causal/counterfactual analysis，以及 2D/3D/video/GUI grounding benchmark 中与幻觉和证据支持相关的论文。",
      "keywords": [
        "hallucination detection",
        "hallucination evaluation",
        "hallucination benchmark",
        "visual hallucination evaluation",
        "object hallucination evaluation",
        "token-level localization",
        "visual evidence",
        "token-level visual evidence",
        "token-level hallucination",
        "visual evidence attribution",
        "visual support",
        "claim-level verification",
        "hallucination detector",
        "attention head analysis",
        "vision-aware head",
        "modality reliance",
        "language prior",
        "visual evidence attrition",
        "visual grounding benchmark",
        "3D visual grounding",
        "GUI grounding",
        "video hallucination",
        "causal intervention hallucination",
        "causal attribution hallucination",
        "counterfactual hallucination",
        "causal mediation",
        "hallucination heads",
        "representation counterfactual"
      ],
      "arxiv_categories": ["cs.CV", "cs.CL", "cs.AI", "cs.LG"]
    }
  ]
}
